ExtendedQtableview/ExtendedQtableview.py
ExtendedQtableview/SQL_table.py
ExtendedQtableview/__init__.py
ExtendedQtableview/testing_file.py
ExtendedQtableview-1.0.5.dist-info/METADATA
ExtendedQtableview-1.0.5.dist-info/WHEEL
ExtendedQtableview-1.0.5.dist-info/top_level.txt
ExtendedQtableview-1.0.5.dist-info/RECORD
