Metadata-Version: 2.1
Name: ExtendedQtableview
Version: 1.0.5
Summary: A custom Qtableview that adds many features for tables, including using SQL, filters, sub-tables, footers, checkboxes and more.. 
Author-email: Jason Fuller <jxfuller1@gmail.com>
Requires-Python: >=3.8
